<?xml version="1.0" encoding="UTF-8"?>
<map>
<cuboid type="accelerate">
	<position x="-2.500000" y="0" z="-1" />
	<size x="5" y="74" z="1.900000" />
	<color x="0.031373" y="0.784314" z="0.356863" />
</cuboid>
<cuboid type="accelerate">
	<position x="-7.000000" y="43" z="1" />
	<size x="2" y="37" z="0.500000" />
	<color x="0.662745" y="0.094118" z="0.101961" />
</cuboid>
<cuboid type="decelerate">
	<position x="-11.500000" y="75" z="-4" />
	<size x="5" y="46" z="4.800000" />
	<color x="0.545098" y="0.882353" z="0.345098" />
</cuboid>
<cuboid type="decelerate">
	<position x="-15.000000" y="129" z="-5" />
	<size x="4" y="60" z="5.600000" />
	<color x="0.819608" y="0.184314" z="0.345098" />
</cuboid>
<cuboid type="accelerate">
	<position x="-12.000000" y="189" z="2" />
	<size x="2" y="69" z="1.000000" />
	<color x="0.800000" y="0.129412" z="0.670588" />
</cuboid>
<cuboid type="decelerate">
	<position x="-16.500000" y="248" z="-8" />
	<size x="3" y="50" z="8.800000" />
	<color x="0.745098" y="0.862745" z="0.878431" />
</cuboid>
<cuboid type="decelerate">
	<position x="-24.500000" y="297" z="-1" />
	<size x="5" y="20" z="3.200000" />
	<color x="0.478431" y="0.886275" z="0.137255" />
</cuboid>
<cuboid type="decelerate">
	<position x="-20.000000" y="351" z="0" />
	<size x="2" y="68" z="4.800000" />
	<color x="0.941176" y="0.627451" z="0.466667" />
</cuboid>
<cuboid type="accelerate">
	<position x="-22.000000" y="397" z="0" />
	<size x="4" y="27" z="4.000000" />
	<color x="0.101961" y="0.901961" z="0.101961" />
</cuboid>
<cuboid type="accelerate">
	<position x="-29.000000" y="450" z="0" />
	<size x="4" y="83" z="5.700000" />
	<color x="0.482353" y="0.654902" z="0.639216" />
</cuboid>
<cuboid type="accelerate">
	<position x="-31.000000" y="505" z="-5" />
	<size x="4" y="58" z="9.700000" />
	<color x="0.729412" y="0.419608" z="0.564706" />
</cuboid>
<cuboid type="accelerate">
	<position x="-28.500000" y="547" z="1" />
	<size x="5" y="23" z="0.700000" />
	<color x="0.600000" y="0.827451" z="0.827451" />
</cuboid>
<cuboid type="decelerate">
	<position x="-34.000000" y="588" z="0" />
	<size x="2" y="92" z="3.800000" />
	<color x="0.552941" y="0.082353" z="0.098039" />
</cuboid>
<cuboid type="accelerate">
	<position x="-38.000000" y="618" z="-3" />
	<size x="4" y="71" z="7.300000" />
	<color x="0.819608" y="0.396078" z="0.337255" />
</cuboid>
<cuboid type="decelerate">
	<position x="-44.000000" y="673" z="0" />
	<size x="4" y="41" z="0.900000" />
	<color x="0.019608" y="0.031373" z="0.086275" />
</cuboid>
<cuboid type="accelerate">
	<position x="-47.500000" y="729" z="-1" />
	<size x="5" y="69" z="2.700000" />
	<color x="0.905882" y="0.462745" z="0.768627" />
</cuboid>
<cuboid type="decelerate">
	<position x="-49.000000" y="784" z="-3" />
	<size x="4" y="48" z="7.100000" />
	<color x="0.792157" y="0.368627" z="0.137255" />
</cuboid>
<cuboid type="accelerate">
	<position x="-55.000000" y="814" z="-3" />
	<size x="4" y="98" z="9.100000" />
	<color x="0.831373" y="0.890196" z="0.721569" />
</cuboid>
<cuboid type="accelerate">
	<position x="-58.000000" y="846" z="-1" />
	<size x="4" y="26" z="5.300000" />
	<color x="0.149020" y="0.105882" z="0.509804" />
</cuboid>
<cuboid type="decelerate">
	<position x="-53.000000" y="890" z="-2" />
	<size x="2" y="78" z="4.000000" />
	<color x="0.874510" y="0.180392" z="0.890196" />
</cuboid>
<cuboid type="decelerate">
	<position x="-60.500000" y="928" z="4" />
	<size x="5" y="32" z="0.300000" />
	<color x="0.458824" y="0.729412" z="0.345098" />
</cuboid>
<cuboid type="accelerate">
	<position x="-54.500000" y="977" z="-2" />
	<size x="5" y="24" z="7.200000" />
	<color x="0.035294" y="0.866667" z="0.631373" />
</cuboid>
<cuboid type="decelerate">
	<position x="-58.000000" y="1013" z="0" />
	<size x="4" y="40" z="2.500000" />
	<color x="0.564706" y="0.200000" z="0.933333" />
</cuboid>
<cuboid type="decelerate">
	<position x="-52.500000" y="1050" z="-2" />
	<size x="3" y="42" z="2.600000" />
	<color x="0.282353" y="0.168627" z="0.800000" />
</cuboid>
<cuboid type="decelerate">
	<position x="-51.000000" y="1082" z="-5" />
	<size x="4" y="59" z="6.800000" />
	<color x="0.580392" y="0.043137" z="0.525490" />
</cuboid>
<cuboid type="decelerate">
	<position x="-57.500000" y="1127" z="-7" />
	<size x="3" y="40" z="8.400000" />
	<color x="0.866667" y="0.149020" z="0.431373" />
</cuboid>
<cuboid type="accelerate">
	<position x="-64.500000" y="1160" z="-8" />
	<size x="3" y="100" z="6.500000" />
	<color x="0.156863" y="0.247059" z="0.862745" />
</cuboid>
<cuboid type="accelerate">
	<position x="-63.500000" y="1192" z="-3" />
	<size x="5" y="62" z="2.300000" />
	<color x="0.980392" y="0.733333" z="0.952941" />
</cuboid>
<cuboid type="accelerate">
	<position x="-69.000000" y="1249" z="-5" />
	<size x="2" y="95" z="3.500000" />
	<color x="0.125490" y="0.023529" z="0.160784" />
</cuboid>
<cuboid type="accelerate">
	<position x="-74.500000" y="1279" z="-5" />
	<size x="5" y="45" z="4.000000" />
	<color x="0.313725" y="0.980392" z="0.050980" />
</cuboid>
<cuboid type="decelerate">
	<position x="-67.500000" y="1331" z="-8" />
	<size x="5" y="89" z="6.800000" />
	<color x="0.368627" y="0.784314" z="0.913725" />
</cuboid>
<cuboid type="accelerate">
	<position x="-59.500000" y="1366" z="-12" />
	<size x="3" y="68" z="7.300000" />
	<color x="0.482353" y="0.686275" z="0.639216" />
</cuboid>
<cuboid type="accelerate">
	<position x="-57.500000" y="1398" z="-5" />
	<size x="3" y="71" z="0.500000" />
	<color x="0.337255" y="0.705882" z="0.588235" />
</cuboid>
<cuboid type="decelerate">
	<position x="-60.000000" y="1440" z="-16" />
	<size x="2" y="70" z="8.400000" />
	<color x="0.615686" y="0.019608" z="0.513725" />
</cuboid>
<cuboid type="decelerate">
	<position x="-66.000000" y="1472" z="-19" />
	<size x="4" y="41" z="9.400000" />
	<color x="0.709804" y="0.882353" z="0.372549" />
</cuboid>
<cuboid type="accelerate">
	<position x="-62.000000" y="1510" z="-21" />
	<size x="4" y="91" z="10.000000" />
	<color x="0.803922" y="0.964706" z="0.674510" />
</cuboid>
<cuboid type="accelerate">
	<position x="-65.500000" y="1546" z="-17" />
	<size x="3" y="64" z="7.000000" />
	<color x="0.854902" y="0.584314" z="0.321569" />
</cuboid>
<cuboid type="accelerate">
	<position x="-65.000000" y="1599" z="-12" />
	<size x="4" y="22" z="4.900000" />
	<color x="0.066667" y="0.717647" z="0.698039" />
</cuboid>
<cuboid type="accelerate">
	<position x="-70.000000" y="1655" z="-10" />
	<size x="2" y="100" z="5.700000" />
	<color x="0.368627" y="0.011765" z="0.768627" />
</cuboid>
<cuboid type="decelerate">
	<position x="-73.000000" y="1704" z="-3" />
	<size x="2" y="93" z="0.500000" />
	<color x="0.415686" y="0.431373" z="0.035294" />
</cuboid>
<cuboid type="accelerate">
	<position x="-67.500000" y="1741" z="-8" />
	<size x="5" y="95" z="5.200000" />
	<color x="0.152941" y="0.301961" z="0.407843" />
</cuboid>
<cuboid type="decelerate">
	<position x="-69.500000" y="1786" z="-3" />
	<size x="3" y="54" z="0.400000" />
	<color x="0.576471" y="0.309804" z="0.545098" />
</cuboid>
<cuboid type="accelerate">
	<position x="-73.000000" y="1836" z="-6" />
	<size x="2" y="46" z="5.100000" />
	<color x="0.352941" y="0.972549" z="0.827451" />
</cuboid>
<cuboid type="accelerate">
	<position x="-79.500000" y="1868" z="-3" />
	<size x="3" y="35" z="4.800000" />
	<color x="0.439216" y="0.156863" z="0.023529" />
</cuboid>
<cuboid type="decelerate">
	<position x="-81.500000" y="1918" z="-7" />
	<size x="3" y="33" z="7.500000" />
	<color x="0.176471" y="0.564706" z="0.521569" />
</cuboid>
<cuboid type="accelerate">
	<position x="-87.000000" y="1948" z="-5" />
	<size x="4" y="58" z="8.300000" />
	<color x="0.686275" y="0.368627" z="0.768627" />
</cuboid>
<cuboid type="accelerate">
	<position x="-87.000000" y="1989" z="-1" />
	<size x="4" y="43" z="3.000000" />
	<color x="0.831373" y="0.149020" z="0.090196" />
</cuboid>
<cuboid type="decelerate">
	<position x="-84.000000" y="2034" z="-9" />
	<size x="2" y="94" z="9.200000" />
	<color x="0.376471" y="0.850980" z="0.580392" />
</cuboid>
<cuboid type="decelerate">
	<position x="-89.000000" y="2083" z="2" />
	<size x="2" y="95" z="0.500000" />
	<color x="0.713725" y="0.933333" z="0.439216" />
</cuboid>
<cuboid type="accelerate">
	<position x="-84.500000" y="2114" z="-1" />
	<size x="3" y="95" z="3.000000" />
	<color x="0.047059" y="0.690196" z="0.423529" />
</cuboid>
<cuboid type="decelerate">
	<position x="-82.500000" y="2166" z="-2" />
	<size x="3" y="95" z="6.200000" />
	<color x="0.784314" y="0.866667" z="0.831373" />
</cuboid>
<cuboid type="accelerate">
	<position x="-90.000000" y="2213" z="-1" />
	<size x="4" y="88" z="4.500000" />
	<color x="0.443137" y="0.149020" z="0.690196" />
</cuboid>
<cuboid type="decelerate">
	<position x="-90.000000" y="2245" z="-1" />
	<size x="2" y="70" z="5.300000" />
	<color x="0.062745" y="0.317647" z="0.521569" />
</cuboid>
<cuboid type="decelerate">
	<position x="-97.000000" y="2294" z="-6" />
	<size x="4" y="46" z="9.800000" />
	<color x="0.211765" y="0.439216" z="0.007843" />
</cuboid>
<cuboid type="decelerate">
	<position x="-91.000000" y="2330" z="0" />
	<size x="4" y="22" z="5.500000" />
	<color x="0.898039" y="0.168627" z="0.176471" />
</cuboid>
<cuboid type="accelerate">
	<position x="-93.000000" y="2384" z="-1" />
	<size x="2" y="35" z="6.400000" />
	<color x="0.349020" y="0.431373" z="0.270588" />
</cuboid>
<cuboid type="decelerate">
	<position x="-99.000000" y="2444" z="-2" />
	<size x="4" y="61" z="5.400000" />
	<color x="0.058824" y="0.141176" z="0.003922" />
</cuboid>
<cuboid type="accelerate">
	<position x="-104.500000" y="2479" z="-4" />
	<size x="5" y="23" z="4.600000" />
	<color x="0.490196" y="0.815686" z="0.243137" />
</cuboid>
<cuboid type="accelerate">
	<position x="-109.500000" y="2530" z="-2" />
	<size x="3" y="58" z="0.500000" />
	<color x="0.298039" y="0.603922" z="0.921569" />
</cuboid>
<cuboid type="decelerate">
	<position x="-111.000000" y="2580" z="-5" />
	<size x="2" y="31" z="2.500000" />
	<color x="0.592157" y="0.105882" z="0.788235" />
</cuboid>
<cuboid type="accelerate">
	<position x="-110.000000" y="2639" z="-11" />
	<size x="2" y="48" z="6.000000" />
	<color x="0.545098" y="0.231373" z="0.211765" />
</cuboid>
<cuboid type="accelerate">
	<position x="-117.500000" y="2685" z="-7" />
	<size x="5" y="93" z="2.500000" />
	<color x="0.239216" y="0.152941" z="0.529412" />
</cuboid>
<cuboid type="decelerate">
	<position x="-123.000000" y="2726" z="-8" />
	<size x="4" y="44" z="6.000000" />
	<color x="0.603922" y="0.556863" z="0.356863" />
</cuboid>
<cuboid type="accelerate">
	<position x="-125.000000" y="2775" z="-5" />
	<size x="4" y="49" z="6.000000" />
	<color x="0.098039" y="0.047059" z="0.317647" />
</cuboid>
<cuboid type="decelerate">
	<position x="-117.500000" y="2830" z="-3" />
	<size x="3" y="26" z="4.000000" />
	<color x="0.490196" y="0.596078" z="0.054902" />
</cuboid>
<cuboid type="accelerate">
	<position x="-121.500000" y="2872" z="-2" />
	<size x="3" y="71" z="2.500000" />
	<color x="0.952941" y="0.317647" z="0.584314" />
</cuboid>
<cuboid type="decelerate">
	<position x="-124.500000" y="2918" z="-3" />
	<size x="5" y="85" z="5.400000" />
	<color x="0.407843" y="0.164706" z="0.976471" />
</cuboid>
<cuboid type="decelerate">
	<position x="-130.500000" y="2965" z="-5" />
	<size x="5" y="37" z="6.800000" />
	<color x="0.823529" y="0.631373" z="0.882353" />
</cuboid>
<cuboid type="decelerate">
	<position x="-132.500000" y="3017" z="-7" />
	<size x="3" y="61" z="7.100000" />
	<color x="0.890196" y="0.549020" z="0.380392" />
</cuboid>
<cuboid type="decelerate">
	<position x="-138.500000" y="3052" z="-3" />
	<size x="3" y="24" z="1.600000" />
	<color x="0.921569" y="0.266667" z="0.207843" />
</cuboid>
<cuboid type="accelerate">
	<position x="-145.500000" y="3084" z="-11" />
	<size x="5" y="80" z="9.500000" />
	<color x="0.929412" y="0.823529" z="0.866667" />
</cuboid>
<cuboid type="decelerate">
	<position x="-144.000000" y="3140" z="-10" />
	<size x="4" y="42" z="6.500000" />
	<color x="0.992157" y="0.349020" z="0.282353" />
</cuboid>
<cuboid type="accelerate">
	<position x="-140.500000" y="3193" z="-8" />
	<size x="3" y="64" z="5.000000" />
	<color x="0.647059" y="0.152941" z="0.003922" />
</cuboid>
<cuboid type="decelerate">
	<position x="-141.000000" y="3239" z="-5" />
	<size x="4" y="79" z="0.900000" />
	<color x="0.988235" y="0.439216" z="0.988235" />
</cuboid>
<cuboid type="decelerate">
	<position x="-138.500000" y="3277" z="-12" />
	<size x="5" y="48" z="9.600000" />
	<color x="0.368627" y="0.682353" z="0.439216" />
</cuboid>
<cuboid type="accelerate">
	<position x="-135.000000" y="3318" z="-2" />
	<size x="4" y="98" z="1.200000" />
	<color x="0.533333" y="0.996078" z="0.901961" />
</cuboid>
<cuboid type="decelerate">
	<position x="-136.000000" y="3361" z="-8" />
	<size x="4" y="27" z="4.000000" />
	<color x="0.956863" y="0.458824" z="0.788235" />
</cuboid>
<cuboid type="accelerate">
	<position x="-132.500000" y="3400" z="-14" />
	<size x="3" y="72" z="9.700000" />
	<color x="0.611765" y="0.968627" z="0.188235" />
</cuboid>
<cuboid type="decelerate">
	<position x="-128.000000" y="3438" z="-9" />
	<size x="2" y="70" z="2.400000" />
	<color x="0.513725" y="0.396078" z="0.647059" />
</cuboid>
<cuboid type="decelerate">
	<position x="-125.000000" y="3488" z="-14" />
	<size x="2" y="38" z="9.500000" />
	<color x="0.321569" y="0.011765" z="0.568627" />
</cuboid>
<cuboid type="accelerate">
	<position x="-123.000000" y="3528" z="-16" />
	<size x="2" y="39" z="8.400000" />
	<color x="0.317647" y="0.501961" z="0.541176" />
</cuboid>
<cuboid type="accelerate">
	<position x="-123.500000" y="3566" z="-11" />
	<size x="5" y="34" z="3.600000" />
	<color x="0.803922" y="0.247059" z="0.956863" />
</cuboid>
<cuboid type="decelerate">
	<position x="-129.000000" y="3615" z="-5" />
	<size x="4" y="41" z="0.300000" />
	<color x="0.160784" y="0.847059" z="0.533333" />
</cuboid>
<cuboid type="decelerate">
	<position x="-134.500000" y="3655" z="-16" />
	<size x="5" y="99" z="8.500000" />
	<color x="0.313725" y="0.113725" z="0.525490" />
</cuboid>
<cuboid type="accelerate">
	<position x="-130.500000" y="3693" z="-16" />
	<size x="5" y="53" z="5.500000" />
	<color x="0.050980" y="0.941176" z="0.027451" />
</cuboid>
<cuboid type="decelerate">
	<position x="-122.500000" y="3743" z="-17" />
	<size x="3" y="52" z="6.600000" />
	<color x="0.168627" y="0.058824" z="0.898039" />
</cuboid>
<cuboid type="accelerate">
	<position x="-122.500000" y="3776" z="-13" />
	<size x="3" y="22" z="3.500000" />
	<color x="0.807843" y="0.200000" z="0.188235" />
</cuboid>
<cuboid type="decelerate">
	<position x="-123.500000" y="3836" z="-18" />
	<size x="3" y="44" z="5.100000" />
	<color x="0.482353" y="0.788235" z="0.027451" />
</cuboid>
<cuboid type="decelerate">
	<position x="-128.500000" y="3877" z="-14" />
	<size x="5" y="42" z="4.100000" />
	<color x="0.454902" y="0.525490" z="0.145098" />
</cuboid>
<cuboid type="accelerate">
	<position x="-130.500000" y="3910" z="-16" />
	<size x="3" y="60" z="4.300000" />
	<color x="0.435294" y="0.078431" z="0.925490" />
</cuboid>
<cuboid type="accelerate">
	<position x="-128.000000" y="3960" z="-12" />
	<size x="4" y="24" z="0.700000" />
	<color x="0.737255" y="0.847059" z="0.443137" />
</cuboid>
<cuboid type="decelerate">
	<position x="-131.000000" y="4016" z="-15" />
	<size x="2" y="100" z="0.500000" />
	<color x="0.576471" y="0.015686" z="0.333333" />
</cuboid>
<cuboid type="decelerate">
	<position x="-126.500000" y="4074" z="-15" />
	<size x="3" y="78" z="2.300000" />
	<color x="0.352941" y="0.211765" z="0.627451" />
</cuboid>
<cuboid type="accelerate">
	<position x="-132.000000" y="4134" z="-22" />
	<size x="2" y="78" z="7.600000" />
	<color x="0.701961" y="0.505882" z="0.121569" />
</cuboid>
<cuboid type="accelerate">
	<position x="-126.000000" y="4177" z="-16" />
	<size x="4" y="87" z="1.000000" />
	<color x="0.145098" y="0.364706" z="0.078431" />
</cuboid>
<cuboid type="decelerate">
	<position x="-119.000000" y="4219" z="-21" />
	<size x="4" y="37" z="6.800000" />
	<color x="0.898039" y="0.623529" z="0.529412" />
</cuboid>
<cuboid type="accelerate">
	<position x="-117.500000" y="4273" z="-18" />
	<size x="3" y="71" z="2.300000" />
	<color x="0.658824" y="0.152941" z="0.450980" />
</cuboid>
<cuboid type="decelerate">
	<position x="-114.000000" y="4303" z="-19" />
	<size x="4" y="89" z="0.400000" />
	<color x="0.721569" y="0.643137" z="1.000000" />
</cuboid>
<cuboid type="accelerate">
	<position x="-107.000000" y="4354" z="-27" />
	<size x="2" y="28" z="8.700000" />
	<color x="0.792157" y="0.262745" z="0.200000" />
</cuboid>
</map>
